{
  "FISHING": [
    "Lavahorse",
    "Gusher",
    "Volcanic Stonefish",
    "Moldfin",
    "Steaming-Hot Flounder",
    "Blobfish",
    "Flyfish"
  ],
  "RESCUE": {
    "Rescue Mission": {
      "item": "abc",
      "location": [
        123,
        123,
        123
      ]
    }
  },
  "FETCH": [
    "Magmag",
    "Spectre Dust",
    "Tentacle Meat",
    "Corrupted Fragment"
  ],
  "DOJO": [
    "Mastery",
    "Tenacity",
    "Stamina",
    "Swiftness",
    "Discipline"
  ],
  "MINIBOSS": [
    "Bladesoul",
    "Mage Outlaw",
    "Barbarian Duke X",
    "Ashfang",
    "Magma Boss"
  ],
  "KUUDRA": [
    "Basic",
    "Hot"
  ]
}